lcss-0.3.1.dist-info/METADATA
lcss-0.3.1.dist-info/WHEEL
lcss-0.3.1.dist-info/entry_points.txt
lcss-0.3.1.dist-info/licenses/LICENSE
lcss/.main.py.swp
lcss/__init__.py
lcss/main.py
lcss-0.3.1.dist-info/RECORD
